flask_july/__init__.py
flask_july/july.py
flask_july-0.2.1.dist-info/METADATA
flask_july-0.2.1.dist-info/WHEEL
flask_july-0.2.1.dist-info/top_level.txt
flask_july-0.2.1.dist-info/RECORD
